crdatamgt/__init__.py
crdatamgt/__main__.py
crdatamgt/formulations.py
crdatamgt/helpers.py
crdatamgt/offlinestats.py
crdatamgt/parameters.yaml
crdatamgt/project.py
crdatamgt/runner.py
crdatamgt/topic.py
crdatamgt-3.0.32.dist-info/WHEEL
crdatamgt-3.0.32.dist-info/METADATA
crdatamgt-3.0.32.dist-info/RECORD
