Metadata-Version: 2.1
Name: crdatamgt
Version: 3.0.32
Summary: 
Author: Your Name
Author-email: you@example.com
Requires-Python: >=3.8.0,<4.0.0
Classifier: Programming Language :: Python :: 3
Classifier: Programming Language :: Python :: 3.8
Requires-Dist: PyYaml (>=5.3.1,<6.0.0)
Requires-Dist: openpyxl (>=3.0.4,<4.0.0)
Requires-Dist: pandas (==1.1.0)
Requires-Dist: simplelogging (>=0.10.0,<0.11.0)
Requires-Dist: toolz (>=0.10.0,<0.11.0)
Requires-Dist: xloaderx (>=0.1.0,<0.2.0)
Requires-Dist: xlsxwriter (>=1.3.0,<2.0.0)
